wyngman/__init__.py
wyngman/aws_arg_parser.py
wyngman/cognito.py
wyngman/constants.py
wyngman/main.py
wyngman/utils.py
wyngman-0.0.4.dist-info/LICENSE
wyngman-0.0.4.dist-info/METADATA
wyngman-0.0.4.dist-info/WHEEL
wyngman-0.0.4.dist-info/entry_points.txt
wyngman-0.0.4.dist-info/top_level.txt
wyngman-0.0.4.dist-info/RECORD
