Metadata-Version: 2.1
Name: wyngman
Version: 0.0.4
Summary: wyngman is a Python package that provides needed functionalities of AWS Toolkit that are otherwise difficult to achieve with the standard cli or not possible currently.
Home-page: https://github.com/Razin-Tailor/wyngman
Author: Razin Tailor
Author-email: razintailorpy@gmail.com
License: MIT
Keywords: AWS,Cognito,amazon web service
Platform: UNKNOWN
Classifier: License :: OSI Approved :: MIT License
Classifier: Programming Language :: Python :: 3
Classifier: Programming Language :: Python :: 3 :: Only
Classifier: Programming Language :: Python :: 3.6
Classifier: Programming Language :: Python :: 3.7
Classifier: Programming Language :: Python :: 3.8
Classifier: Programming Language :: Python :: 3.9
Classifier: Programming Language :: Python :: 3.10
Classifier: Programming Language :: Python :: Implementation :: CPython
Classifier: Programming Language :: Python :: Implementation :: PyPy
Requires-Python: >=3.6.1
License-File: LICENSE
Requires-Dist: boto3
Requires-Dist: halo
Requires-Dist: pandas (>=1.2)
Requires-Dist: pyfiglet
Requires-Dist: python-dotenv
Requires-Dist: tabulate
Requires-Dist: PyInquirer
Requires-Dist: importlib-resources ; python_version < "3.7"
Requires-Dist: importlib-metadata ; python_version < "3.8"
